s3dbm/__init__.py
s3dbm/main.py
s3dbm/utils.py
s3dbm/tests/__init__.py
s3dbm-0.0.8.dist-info/LICENSE
s3dbm-0.0.8.dist-info/METADATA
s3dbm-0.0.8.dist-info/WHEEL
s3dbm-0.0.8.dist-info/top_level.txt
s3dbm-0.0.8.dist-info/RECORD
