Metadata-Version: 2.1
Name: s3dbm
Version: 0.0.8
Summary: A python dbm-style interface to S3
Home-page: https://github.com/mullenkamp/s3dbm
Author: Mike Kittridge
Author-email: mullenkamp1@gmail.com
License: Apache
Keywords: shelve dbm s3
Classifier: Development Status :: 3 - Alpha
Classifier: Intended Audience :: Developers
Classifier: License :: OSI Approved :: Apache Software License
Classifier: Programming Language :: Python :: 3.8
Classifier: Programming Language :: Python :: 3.9
License-File: LICENSE
Requires-Dist: boto3
Requires-Dist: pydantic
Requires-Dist: smart-open
Requires-Dist: zstandard
